xnatqa/__init__.py
xnatqa/launch.py
xnatqa/xnatqa.py
xnatqa/tag/__init__.py
xnatqa-0.0.21.dist-info/licenses/LICENSE
xnatqa-0.0.21.dist-info/METADATA
xnatqa-0.0.21.dist-info/WHEEL
xnatqa-0.0.21.dist-info/entry_points.txt
xnatqa-0.0.21.dist-info/top_level.txt
xnatqa-0.0.21.dist-info/RECORD
