Metadata-Version: 2.4
Name: xnatqa
Version: 0.0.21
Summary: A workflow for automatically tagging MRI scans within XNAT
Author-email: Kyle Kurkela <kkurkela@bu.edu>
License-Expression: MIT
Project-URL: Homepage, https://github.com/kakurk/auto_labeler
Project-URL: Issues, https://github.com/kakurk/auto_labeler/issues
Classifier: Programming Language :: Python :: 3
Classifier: Operating System :: OS Independent
Requires-Python: >=3.9
License-File: LICENSE
Requires-Dist: xnattagger-kkurk
Requires-Dist: yaxil
Requires-Dist: pyyaml
Requires-Dist: glob2
Dynamic: license-file
